{
	"operationId":"ManagePlacardAction.editTemplet",
	"summary":"summary",
	"description":"description",
	"produces":[
		"application/json"
	],
	"consumes":[
		"application/x-www-form-urlencoded"
	],
	"parameters":[
		{
			"type":"integer",
			"format":"int64",
			"name":"id",
			"description":"id",
			"in":"formData",
			"required":true
		},
		{
			"type":"string",
			"name":"title",
			"description":"title",
			"in":"formData",
			"required":true
		},
		{
			"type":"string",
			"name":"content",
			"description":"content",
			"in":"formData",
			"required":true
		},
		{
			"type":"string",
			"name":"end_rime",
			"description":"end_rime",
			"in":"formData",
			"required":true
		},
		{
			"type":"boolean",
			"name":"disable_flag",
			"description":"disable_flag",
			"in":"formData",
			"required":true
		},
		{
			"type":"integer",
			"format":"int32",
			"name":"link_type",
			"description":"link_type",
			"in":"formData",
			"default":0,
			"required":false
		},
		{
			"type":"string",
			"name":"link_data",
			"description":"link_data",
			"in":"formData",
			"required":true
		}
	],
	"responses":{
		"200":{
			"schema":{
				"type":"string"
			},
			"description":"response"
		},
		"404":{
			"description":"路径不存在"
		}
	}
}