{
                "summary": "获取一个类目下置顶的文章id列表",
                "tags": [
                    "posttop",
                    "admin",
                    "get"
                ],
                "description": "获取一个类目下置顶的文章id列表",
                "parameters": [
                    {
                        "$ref": "#/parameters/apiKeyYHeader"
                    },
                    {
                        "$ref": "#/parameters/categoryPath"
                    }
                ],
                "responses": {
                    "200": {
                        "schema": {
                            "$ref": "#/definitions/PostTop"
                        },
                        "description": "PostTop响应对象"
                    }
                },
                "operationId": "getTopPosts"
            }