{
    "summary": "User退出登录",
    "tags": 
    [
        "users"
    ],

    "description": "User退出登录",

    "consumes": 
	[
		"application/x-www-form-urlencoded"
	],

    "parameters": 
    [
    	{
            "$ref": "#/parameters/apiKeyYHeader"
        },
        
        {
            "$ref": "#/parameters/userPath"
        },
        
    	{
			"description": "设备编号:1：web；2：ios；3：android",
			"name": "device",
			"type": "integer",
			"format":"int32",
			"required": true,
			"in": "formData"
		},
		
		{
			"description": "设备id",
			"name": "deviceId",
			"type": "string",
			"required": false,
			"in": "formData"
		}
    ],

    "responses": 
    {
        "200": 
        {
        	"schema": 
			{
				"$ref": "#/definitions/Success"
			},
            "description": "退出成功"
        }
    },

    "operationId": "logoutUser"
}