{
    "description": "elearning测试类目",
    "properties": 
    {
        "id": 
        {
            "description": "id",
            "type": "string"
        },
        "name": 
        {
            "description": "类目名称",
            "type": "string"
        },
        "image": 
        {
            "description": "类目图片地址",
            "type": "string"
        },
        "parentId": 
        {
            "description": "父目录Id",
            "type": "string"
        },
        "cats": 
        {
            "description": "子类目",
            "type": "array",
            "items": 
            {
                "$ref": "#/definitions/ElearningQuizCategory"
            }
        },
        "type": 
        {
            "description": "类目对应的页面类型：1-视频列表  | 2-文章列表 | 3-测试",
            "format": "int32",
            "type": "integer"
        }
    }
}